orby/__about__.py
orby/__init__.py
orby-0.1.0a0.dist-info/METADATA
orby-0.1.0a0.dist-info/WHEEL
orby-0.1.0a0.dist-info/licenses/LICENSE
orby-0.1.0a0.dist-info/RECORD
